spacy_preprocessing/__init__.py
spacy_preprocessing/preprocess.py
spacy_preprocessing/data/IWNLP.Lemmatizer_20181001.json
spacy_german_preprocess-0.0.2.dist-info/LICENSE
spacy_german_preprocess-0.0.2.dist-info/METADATA
spacy_german_preprocess-0.0.2.dist-info/WHEEL
spacy_german_preprocess-0.0.2.dist-info/top_level.txt
spacy_german_preprocess-0.0.2.dist-info/RECORD
