Metadata-Version: 2.1
Name: spacy-german-preprocess
Version: 0.0.2
Summary: A small package for preprocessing german text
Home-page: https://github.com/Mistscream/spacy_german_preprocessing
Author: Sebastian Jüngling
Author-email: author@example.com
License: UNKNOWN
Platform: UNKNOWN
Classifier: Programming Language :: Python :: 3
Classifier: License :: OSI Approved :: MIT License
Classifier: Operating System :: OS Independent
Requires-Dist: spacy
Requires-Dist: spacy-iwnlp
